{
  "openapi": "3.1.0",
  "info": {
    "title": "Otto Internal Tool API",
    "version": "1.0.0",
    "description": "Internal API for Otto tool adapters and automation flows. This API is intended for local/runtime tooling integration and is not a public compatibility contract."
  },
  "tags": [
    {
      "name": "Tools",
      "description": "Internal tool execution endpoints"
    },
    {
      "name": "BackgroundJobs",
      "description": "Interactive background job operations"
    },
    {
      "name": "Tasks",
      "description": "Task scheduling and audit operations"
    },
    {
      "name": "Telegram",
      "description": "Outbound Telegram queue operations"
    }
  ],
  "components": {
    "securitySchemes": {
      "bearerAuth": {
        "type": "http",
        "scheme": "bearer"
      }
    }
  },
  "paths": {
    "/internal/tools/queue-telegram-message": {
      "post": {
        "tags": [
          "Telegram"
        ],
        "summary": "Queue outbound Telegram text message",
        "requestBody": {
          "required": true,
          "content": {
            "application/json": {
              "schema": {
                "type": "object",
                "properties": {
                  "sessionId": {
                    "type": "string",
                    "minLength": 1
                  },
                  "chatId": {
                    "type": "integer",
                    "minimum": -9007199254740991,
                    "maximum": 9007199254740991
                  },
                  "content": {
                    "type": "string",
                    "minLength": 1
                  },
                  "dedupeKey": {
                    "type": "string",
                    "minLength": 1,
                    "maxLength": 512
                  },
                  "priority": {
                    "type": "string",
                    "enum": [
                      "low",
                      "normal",
                      "high",
                      "critical"
                    ]
                  }
                },
                "required": [
                  "content"
                ],
                "additionalProperties": false
              }
            }
          }
        },
        "responses": {
          "200": {
            "description": "Queue result",
            "content": {
              "application/json": {
                "schema": {
                  "type": "object",
                  "properties": {
                    "status": {
                      "type": "string",
                      "enum": [
                        "enqueued",
                        "duplicate"
                      ]
                    },
                    "queuedCount": {
                      "type": "integer",
                      "minimum": -9007199254740991,
                      "maximum": 9007199254740991
                    },
                    "duplicateCount": {
                      "type": "integer",
                      "minimum": -9007199254740991,
                      "maximum": 9007199254740991
                    },
                    "dedupeKey": {
                      "anyOf": [
                        {
                          "type": "string"
                        },
                        {
                          "type": "null"
                        }
                      ]
                    },
                    "messageIds": {
                      "type": "array",
                      "items": {
                        "type": "string"
                      }
                    }
                  },
                  "required": [
                    "status",
                    "queuedCount",
                    "duplicateCount",
                    "dedupeKey",
                    "messageIds"
                  ],
                  "additionalProperties": false
                }
              }
            }
          },
          "400": {
            "description": "Invalid request",
            "content": {
              "application/json": {
                "schema": {
                  "anyOf": [
                    {
                      "type": "object",
                      "properties": {
                        "error": {
                          "type": "string",
                          "const": "invalid_request"
                        },
                        "details": {
                          "type": "array",
                          "items": {}
                        }
                      },
                      "required": [
                        "error"
                      ],
                      "additionalProperties": false
                    },
                    {
                      "type": "object",
                      "properties": {
                        "error": {
                          "type": "string",
                          "const": "missing_chat"
                        },
                        "message": {
                          "type": "string",
                          "minLength": 1
                        }
                      },
                      "required": [
                        "error",
                        "message"
                      ],
                      "additionalProperties": false
                    }
                  ]
                }
              }
            }
          },
          "401": {
            "description": "Unauthorized",
            "content": {
              "application/json": {
                "schema": {
                  "type": "object",
                  "properties": {
                    "error": {
                      "type": "string",
                      "const": "unauthorized"
                    }
                  },
                  "required": [
                    "error"
                  ],
                  "additionalProperties": false
                }
              }
            }
          },
          "500": {
            "description": "Internal error",
            "content": {
              "application/json": {
                "schema": {
                  "type": "object",
                  "properties": {
                    "error": {
                      "type": "string",
                      "const": "internal_error"
                    }
                  },
                  "required": [
                    "error"
                  ],
                  "additionalProperties": false
                }
              }
            }
          }
        },
        "security": [
          {
            "bearerAuth": []
          }
        ]
      }
    },
    "/internal/tools/queue-telegram-file": {
      "post": {
        "tags": [
          "Telegram"
        ],
        "summary": "Queue outbound Telegram file",
        "requestBody": {
          "required": true,
          "content": {
            "application/json": {
              "schema": {
                "type": "object",
                "properties": {
                  "sessionId": {
                    "type": "string",
                    "minLength": 1
                  },
                  "chatId": {
                    "type": "integer",
                    "minimum": -9007199254740991,
                    "maximum": 9007199254740991
                  },
                  "kind": {
                    "type": "string",
                    "enum": [
                      "document",
                      "photo"
                    ]
                  },
                  "filePath": {
                    "type": "string",
                    "minLength": 1
                  },
                  "mimeType": {
                    "type": "string",
                    "minLength": 1
                  },
                  "fileName": {
                    "type": "string",
                    "minLength": 1
                  },
                  "caption": {
                    "type": "string",
                    "maxLength": 4000
                  },
                  "dedupeKey": {
                    "type": "string",
                    "minLength": 1,
                    "maxLength": 512
                  },
                  "priority": {
                    "type": "string",
                    "enum": [
                      "low",
                      "normal",
                      "high",
                      "critical"
                    ]
                  }
                },
                "required": [
                  "kind",
                  "filePath",
                  "mimeType"
                ],
                "additionalProperties": false
              }
            }
          }
        },
        "responses": {
          "200": {
            "description": "Queue result",
            "content": {
              "application/json": {
                "schema": {
                  "type": "object",
                  "properties": {
                    "status": {
                      "type": "string",
                      "enum": [
                        "enqueued",
                        "duplicate"
                      ]
                    },
                    "queuedCount": {
                      "type": "integer",
                      "minimum": -9007199254740991,
                      "maximum": 9007199254740991
                    },
                    "duplicateCount": {
                      "type": "integer",
                      "minimum": -9007199254740991,
                      "maximum": 9007199254740991
                    },
                    "dedupeKey": {
                      "anyOf": [
                        {
                          "type": "string"
                        },
                        {
                          "type": "null"
                        }
                      ]
                    },
                    "messageIds": {
                      "type": "array",
                      "items": {
                        "type": "string"
                      }
                    }
                  },
                  "required": [
                    "status",
                    "queuedCount",
                    "duplicateCount",
                    "dedupeKey",
                    "messageIds"
                  ],
                  "additionalProperties": false
                }
              }
            }
          },
          "400": {
            "description": "Invalid request",
            "content": {
              "application/json": {
                "schema": {
                  "anyOf": [
                    {
                      "type": "object",
                      "properties": {
                        "error": {
                          "type": "string",
                          "const": "invalid_request"
                        },
                        "details": {
                          "type": "array",
                          "items": {}
                        }
                      },
                      "required": [
                        "error"
                      ],
                      "additionalProperties": false
                    },
                    {
                      "type": "object",
                      "properties": {
                        "error": {
                          "type": "string",
                          "const": "missing_chat"
                        },
                        "message": {
                          "type": "string",
                          "minLength": 1
                        }
                      },
                      "required": [
                        "error",
                        "message"
                      ],
                      "additionalProperties": false
                    },
                    {
                      "type": "object",
                      "properties": {
                        "error": {
                          "type": "string",
                          "const": "invalid_file_path"
                        },
                        "message": {
                          "type": "string",
                          "minLength": 1
                        }
                      },
                      "required": [
                        "error",
                        "message"
                      ],
                      "additionalProperties": false
                    },
                    {
                      "type": "object",
                      "properties": {
                        "error": {
                          "type": "string",
                          "const": "file_too_large"
                        },
                        "message": {
                          "type": "string",
                          "minLength": 1
                        }
                      },
                      "required": [
                        "error",
                        "message"
                      ],
                      "additionalProperties": false
                    }
                  ]
                }
              }
            }
          },
          "401": {
            "description": "Unauthorized",
            "content": {
              "application/json": {
                "schema": {
                  "type": "object",
                  "properties": {
                    "error": {
                      "type": "string",
                      "const": "unauthorized"
                    }
                  },
                  "required": [
                    "error"
                  ],
                  "additionalProperties": false
                }
              }
            }
          },
          "500": {
            "description": "Internal error",
            "content": {
              "application/json": {
                "schema": {
                  "type": "object",
                  "properties": {
                    "error": {
                      "type": "string",
                      "const": "internal_error"
                    }
                  },
                  "required": [
                    "error"
                  ],
                  "additionalProperties": false
                }
              }
            }
          }
        },
        "security": [
          {
            "bearerAuth": []
          }
        ]
      }
    },
    "/internal/tools/tasks/create": {
      "post": {
        "tags": [
          "Tasks"
        ],
        "summary": "Create task",
        "requestBody": {
          "required": true,
          "content": {
            "application/json": {
              "schema": {
                "type": "object",
                "properties": {
                  "lane": {
                    "type": "string",
                    "enum": [
                      "interactive",
                      "scheduled"
                    ]
                  },
                  "id": {
                    "type": "string",
                    "minLength": 1
                  },
                  "type": {
                    "type": "string",
                    "minLength": 1
                  },
                  "scheduleType": {
                    "type": "string",
                    "enum": [
                      "recurring",
                      "oneshot"
                    ]
                  },
                  "runAt": {
                    "type": "integer",
                    "minimum": -9007199254740991,
                    "maximum": 9007199254740991
                  },
                  "cadenceMinutes": {
                    "type": "integer",
                    "minimum": 1,
                    "maximum": 9007199254740991
                  },
                  "payload": {
                    "type": "object",
                    "propertyNames": {
                      "type": "string"
                    },
                    "additionalProperties": {}
                  },
                  "profileId": {
                    "type": "string",
                    "minLength": 1
                  }
                },
                "required": [
                  "lane",
                  "type",
                  "scheduleType"
                ],
                "additionalProperties": false
              }
            }
          }
        },
        "responses": {
          "200": {
            "description": "Task created",
            "content": {
              "application/json": {
                "schema": {
                  "type": "object",
                  "propertyNames": {
                    "type": "string"
                  },
                  "additionalProperties": {}
                }
              }
            }
          },
          "400": {
            "description": "Invalid request",
            "content": {
              "application/json": {
                "schema": {
                  "type": "object",
                  "properties": {
                    "error": {
                      "type": "string",
                      "const": "invalid_request"
                    },
                    "details": {
                      "type": "array",
                      "items": {}
                    }
                  },
                  "required": [
                    "error"
                  ],
                  "additionalProperties": false
                }
              }
            }
          },
          "401": {
            "description": "Unauthorized",
            "content": {
              "application/json": {
                "schema": {
                  "type": "object",
                  "properties": {
                    "error": {
                      "type": "string",
                      "const": "unauthorized"
                    }
                  },
                  "required": [
                    "error"
                  ],
                  "additionalProperties": false
                }
              }
            }
          },
          "403": {
            "description": "Lane forbidden",
            "content": {
              "application/json": {
                "schema": {
                  "type": "object",
                  "properties": {
                    "error": {
                      "type": "string",
                      "const": "lane_forbidden"
                    },
                    "message": {
                      "type": "string",
                      "minLength": 1
                    }
                  },
                  "required": [
                    "error",
                    "message"
                  ],
                  "additionalProperties": false
                }
              }
            }
          },
          "500": {
            "description": "Internal error",
            "content": {
              "application/json": {
                "schema": {
                  "type": "object",
                  "properties": {
                    "error": {
                      "type": "string",
                      "const": "internal_error"
                    }
                  },
                  "required": [
                    "error"
                  ],
                  "additionalProperties": false
                }
              }
            }
          }
        },
        "security": [
          {
            "bearerAuth": []
          }
        ]
      }
    },
    "/internal/tools/background-jobs/spawn": {
      "post": {
        "tags": [
          "BackgroundJobs"
        ],
        "summary": "Spawn interactive background job",
        "requestBody": {
          "required": true,
          "content": {
            "application/json": {
              "schema": {
                "type": "object",
                "properties": {
                  "lane": {
                    "default": "interactive",
                    "type": "string",
                    "enum": [
                      "interactive",
                      "scheduled"
                    ]
                  },
                  "sessionId": {
                    "type": "string",
                    "minLength": 1
                  },
                  "request": {
                    "type": "string",
                    "minLength": 1
                  },
                  "rationale": {
                    "type": "string",
                    "minLength": 1,
                    "maxLength": 500
                  },
                  "sourceMessageId": {
                    "type": "string",
                    "minLength": 1
                  }
                },
                "required": [
                  "lane",
                  "request"
                ],
                "additionalProperties": false
              }
            }
          }
        },
        "responses": {
          "200": {
            "description": "Background job spawned",
            "content": {
              "application/json": {
                "schema": {
                  "type": "object",
                  "propertyNames": {
                    "type": "string"
                  },
                  "additionalProperties": {}
                }
              }
            }
          },
          "400": {
            "description": "Invalid request",
            "content": {
              "application/json": {
                "schema": {
                  "type": "object",
                  "properties": {
                    "error": {
                      "type": "string",
                      "const": "invalid_request"
                    },
                    "details": {
                      "type": "array",
                      "items": {}
                    }
                  },
                  "required": [
                    "error"
                  ],
                  "additionalProperties": false
                }
              }
            }
          },
          "401": {
            "description": "Unauthorized",
            "content": {
              "application/json": {
                "schema": {
                  "type": "object",
                  "properties": {
                    "error": {
                      "type": "string",
                      "const": "unauthorized"
                    }
                  },
                  "required": [
                    "error"
                  ],
                  "additionalProperties": false
                }
              }
            }
          },
          "500": {
            "description": "Internal error",
            "content": {
              "application/json": {
                "schema": {
                  "type": "object",
                  "properties": {
                    "error": {
                      "type": "string",
                      "const": "internal_error"
                    }
                  },
                  "required": [
                    "error"
                  ],
                  "additionalProperties": false
                }
              }
            }
          }
        },
        "security": [
          {
            "bearerAuth": []
          }
        ]
      }
    },
    "/internal/tools/background-jobs/milestone": {
      "post": {
        "tags": [
          "BackgroundJobs"
        ],
        "summary": "Report background job milestone",
        "requestBody": {
          "required": true,
          "content": {
            "application/json": {
              "schema": {
                "type": "object",
                "properties": {
                  "lane": {
                    "default": "interactive",
                    "type": "string",
                    "enum": [
                      "interactive",
                      "scheduled"
                    ]
                  },
                  "sessionId": {
                    "type": "string",
                    "minLength": 1
                  },
                  "taskId": {
                    "type": "string",
                    "minLength": 1
                  },
                  "runId": {
                    "type": "string",
                    "minLength": 1
                  },
                  "chatId": {
                    "type": "integer",
                    "exclusiveMinimum": 0,
                    "maximum": 9007199254740991
                  },
                  "content": {
                    "type": "string",
                    "minLength": 1
                  }
                },
                "required": [
                  "lane",
                  "content"
                ],
                "additionalProperties": false
              }
            }
          }
        },
        "responses": {
          "200": {
            "description": "Milestone accepted",
            "content": {
              "application/json": {
                "schema": {
                  "type": "object",
                  "propertyNames": {
                    "type": "string"
                  },
                  "additionalProperties": {}
                }
              }
            }
          },
          "400": {
            "description": "Invalid request",
            "content": {
              "application/json": {
                "schema": {
                  "type": "object",
                  "properties": {
                    "error": {
                      "type": "string",
                      "const": "invalid_request"
                    },
                    "details": {
                      "type": "array",
                      "items": {}
                    }
                  },
                  "required": [
                    "error"
                  ],
                  "additionalProperties": false
                }
              }
            }
          },
          "401": {
            "description": "Unauthorized",
            "content": {
              "application/json": {
                "schema": {
                  "type": "object",
                  "properties": {
                    "error": {
                      "type": "string",
                      "const": "unauthorized"
                    }
                  },
                  "required": [
                    "error"
                  ],
                  "additionalProperties": false
                }
              }
            }
          },
          "500": {
            "description": "Internal error",
            "content": {
              "application/json": {
                "schema": {
                  "type": "object",
                  "properties": {
                    "error": {
                      "type": "string",
                      "const": "internal_error"
                    }
                  },
                  "required": [
                    "error"
                  ],
                  "additionalProperties": false
                }
              }
            }
          }
        },
        "security": [
          {
            "bearerAuth": []
          }
        ]
      }
    },
    "/internal/tools/background-jobs/list": {
      "post": {
        "tags": [
          "BackgroundJobs"
        ],
        "summary": "List background jobs",
        "requestBody": {
          "required": true,
          "content": {
            "application/json": {
              "schema": {
                "type": "object",
                "properties": {
                  "lane": {
                    "default": "interactive",
                    "type": "string",
                    "enum": [
                      "interactive",
                      "scheduled"
                    ]
                  },
                  "limit": {
                    "type": "integer",
                    "minimum": 1,
                    "maximum": 200
                  }
                },
                "required": [
                  "lane"
                ],
                "additionalProperties": false
              }
            }
          }
        },
        "responses": {
          "200": {
            "description": "Background jobs list",
            "content": {
              "application/json": {
                "schema": {
                  "type": "object",
                  "propertyNames": {
                    "type": "string"
                  },
                  "additionalProperties": {}
                }
              }
            }
          },
          "400": {
            "description": "Invalid request",
            "content": {
              "application/json": {
                "schema": {
                  "type": "object",
                  "properties": {
                    "error": {
                      "type": "string",
                      "const": "invalid_request"
                    },
                    "details": {
                      "type": "array",
                      "items": {}
                    }
                  },
                  "required": [
                    "error"
                  ],
                  "additionalProperties": false
                }
              }
            }
          },
          "401": {
            "description": "Unauthorized",
            "content": {
              "application/json": {
                "schema": {
                  "type": "object",
                  "properties": {
                    "error": {
                      "type": "string",
                      "const": "unauthorized"
                    }
                  },
                  "required": [
                    "error"
                  ],
                  "additionalProperties": false
                }
              }
            }
          },
          "403": {
            "description": "Lane forbidden",
            "content": {
              "application/json": {
                "schema": {
                  "type": "object",
                  "properties": {
                    "error": {
                      "type": "string",
                      "const": "lane_forbidden"
                    },
                    "message": {
                      "type": "string",
                      "minLength": 1
                    }
                  },
                  "required": [
                    "error",
                    "message"
                  ],
                  "additionalProperties": false
                }
              }
            }
          },
          "500": {
            "description": "Internal error",
            "content": {
              "application/json": {
                "schema": {
                  "type": "object",
                  "properties": {
                    "error": {
                      "type": "string",
                      "const": "internal_error"
                    }
                  },
                  "required": [
                    "error"
                  ],
                  "additionalProperties": false
                }
              }
            }
          }
        },
        "security": [
          {
            "bearerAuth": []
          }
        ]
      }
    },
    "/internal/tools/background-jobs/show": {
      "post": {
        "tags": [
          "BackgroundJobs"
        ],
        "summary": "Show background job details",
        "requestBody": {
          "required": true,
          "content": {
            "application/json": {
              "schema": {
                "type": "object",
                "properties": {
                  "lane": {
                    "default": "interactive",
                    "type": "string",
                    "enum": [
                      "interactive",
                      "scheduled"
                    ]
                  },
                  "jobId": {
                    "type": "string",
                    "minLength": 1
                  }
                },
                "required": [
                  "lane",
                  "jobId"
                ],
                "additionalProperties": false
              }
            }
          }
        },
        "responses": {
          "200": {
            "description": "Background job details",
            "content": {
              "application/json": {
                "schema": {
                  "type": "object",
                  "propertyNames": {
                    "type": "string"
                  },
                  "additionalProperties": {}
                }
              }
            }
          },
          "400": {
            "description": "Invalid request",
            "content": {
              "application/json": {
                "schema": {
                  "type": "object",
                  "properties": {
                    "error": {
                      "type": "string",
                      "const": "invalid_request"
                    },
                    "details": {
                      "type": "array",
                      "items": {}
                    }
                  },
                  "required": [
                    "error"
                  ],
                  "additionalProperties": false
                }
              }
            }
          },
          "401": {
            "description": "Unauthorized",
            "content": {
              "application/json": {
                "schema": {
                  "type": "object",
                  "properties": {
                    "error": {
                      "type": "string",
                      "const": "unauthorized"
                    }
                  },
                  "required": [
                    "error"
                  ],
                  "additionalProperties": false
                }
              }
            }
          },
          "403": {
            "description": "Lane forbidden",
            "content": {
              "application/json": {
                "schema": {
                  "type": "object",
                  "properties": {
                    "error": {
                      "type": "string",
                      "const": "lane_forbidden"
                    },
                    "message": {
                      "type": "string",
                      "minLength": 1
                    }
                  },
                  "required": [
                    "error",
                    "message"
                  ],
                  "additionalProperties": false
                }
              }
            }
          },
          "404": {
            "description": "Not found",
            "content": {
              "application/json": {
                "schema": {
                  "type": "object",
                  "properties": {
                    "error": {
                      "type": "string",
                      "const": "not_found"
                    },
                    "message": {
                      "type": "string"
                    }
                  },
                  "required": [
                    "error"
                  ],
                  "additionalProperties": false
                }
              }
            }
          },
          "500": {
            "description": "Internal error",
            "content": {
              "application/json": {
                "schema": {
                  "type": "object",
                  "properties": {
                    "error": {
                      "type": "string",
                      "const": "internal_error"
                    }
                  },
                  "required": [
                    "error"
                  ],
                  "additionalProperties": false
                }
              }
            }
          }
        },
        "security": [
          {
            "bearerAuth": []
          }
        ]
      }
    },
    "/internal/tools/background-jobs/cancel": {
      "post": {
        "tags": [
          "BackgroundJobs"
        ],
        "summary": "Cancel background job",
        "requestBody": {
          "required": true,
          "content": {
            "application/json": {
              "schema": {
                "type": "object",
                "properties": {
                  "lane": {
                    "default": "interactive",
                    "type": "string",
                    "enum": [
                      "interactive",
                      "scheduled"
                    ]
                  },
                  "jobId": {
                    "type": "string",
                    "minLength": 1
                  },
                  "reason": {
                    "type": "string",
                    "minLength": 1
                  }
                },
                "required": [
                  "lane",
                  "jobId"
                ],
                "additionalProperties": false
              }
            }
          }
        },
        "responses": {
          "200": {
            "description": "Background job cancelled",
            "content": {
              "application/json": {
                "schema": {
                  "type": "object",
                  "propertyNames": {
                    "type": "string"
                  },
                  "additionalProperties": {}
                }
              }
            }
          },
          "400": {
            "description": "Invalid request",
            "content": {
              "application/json": {
                "schema": {
                  "type": "object",
                  "properties": {
                    "error": {
                      "type": "string",
                      "const": "invalid_request"
                    },
                    "details": {
                      "type": "array",
                      "items": {}
                    }
                  },
                  "required": [
                    "error"
                  ],
                  "additionalProperties": false
                }
              }
            }
          },
          "401": {
            "description": "Unauthorized",
            "content": {
              "application/json": {
                "schema": {
                  "type": "object",
                  "properties": {
                    "error": {
                      "type": "string",
                      "const": "unauthorized"
                    }
                  },
                  "required": [
                    "error"
                  ],
                  "additionalProperties": false
                }
              }
            }
          },
          "403": {
            "description": "Lane forbidden",
            "content": {
              "application/json": {
                "schema": {
                  "type": "object",
                  "properties": {
                    "error": {
                      "type": "string",
                      "const": "lane_forbidden"
                    },
                    "message": {
                      "type": "string",
                      "minLength": 1
                    }
                  },
                  "required": [
                    "error",
                    "message"
                  ],
                  "additionalProperties": false
                }
              }
            }
          },
          "404": {
            "description": "Not found",
            "content": {
              "application/json": {
                "schema": {
                  "type": "object",
                  "properties": {
                    "error": {
                      "type": "string",
                      "const": "not_found"
                    },
                    "message": {
                      "type": "string"
                    }
                  },
                  "required": [
                    "error"
                  ],
                  "additionalProperties": false
                }
              }
            }
          },
          "500": {
            "description": "Internal error",
            "content": {
              "application/json": {
                "schema": {
                  "type": "object",
                  "properties": {
                    "error": {
                      "type": "string",
                      "const": "internal_error"
                    }
                  },
                  "required": [
                    "error"
                  ],
                  "additionalProperties": false
                }
              }
            }
          }
        },
        "security": [
          {
            "bearerAuth": []
          }
        ]
      }
    },
    "/internal/tools/tasks/update": {
      "post": {
        "tags": [
          "Tasks"
        ],
        "summary": "Update task",
        "requestBody": {
          "required": true,
          "content": {
            "application/json": {
              "schema": {
                "type": "object",
                "properties": {
                  "lane": {
                    "type": "string",
                    "enum": [
                      "interactive",
                      "scheduled"
                    ]
                  },
                  "id": {
                    "type": "string",
                    "minLength": 1
                  },
                  "type": {
                    "type": "string",
                    "minLength": 1
                  },
                  "scheduleType": {
                    "type": "string",
                    "enum": [
                      "recurring",
                      "oneshot"
                    ]
                  },
                  "runAt": {
                    "anyOf": [
                      {
                        "type": "integer",
                        "minimum": -9007199254740991,
                        "maximum": 9007199254740991
                      },
                      {
                        "type": "null"
                      }
                    ]
                  },
                  "cadenceMinutes": {
                    "anyOf": [
                      {
                        "type": "integer",
                        "minimum": 1,
                        "maximum": 9007199254740991
                      },
                      {
                        "type": "null"
                      }
                    ]
                  },
                  "payload": {
                    "anyOf": [
                      {
                        "type": "object",
                        "propertyNames": {
                          "type": "string"
                        },
                        "additionalProperties": {}
                      },
                      {
                        "type": "null"
                      }
                    ]
                  },
                  "profileId": {
                    "anyOf": [
                      {
                        "type": "string",
                        "minLength": 1
                      },
                      {
                        "type": "null"
                      }
                    ]
                  }
                },
                "required": [
                  "lane",
                  "id"
                ],
                "additionalProperties": false
              }
            }
          }
        },
        "responses": {
          "200": {
            "description": "Task updated",
            "content": {
              "application/json": {
                "schema": {
                  "type": "object",
                  "propertyNames": {
                    "type": "string"
                  },
                  "additionalProperties": {}
                }
              }
            }
          },
          "400": {
            "description": "Invalid request",
            "content": {
              "application/json": {
                "schema": {
                  "type": "object",
                  "properties": {
                    "error": {
                      "type": "string",
                      "const": "invalid_request"
                    },
                    "details": {
                      "type": "array",
                      "items": {}
                    }
                  },
                  "required": [
                    "error"
                  ],
                  "additionalProperties": false
                }
              }
            }
          },
          "401": {
            "description": "Unauthorized",
            "content": {
              "application/json": {
                "schema": {
                  "type": "object",
                  "properties": {
                    "error": {
                      "type": "string",
                      "const": "unauthorized"
                    }
                  },
                  "required": [
                    "error"
                  ],
                  "additionalProperties": false
                }
              }
            }
          },
          "403": {
            "description": "Lane forbidden",
            "content": {
              "application/json": {
                "schema": {
                  "type": "object",
                  "properties": {
                    "error": {
                      "type": "string",
                      "const": "lane_forbidden"
                    },
                    "message": {
                      "type": "string",
                      "minLength": 1
                    }
                  },
                  "required": [
                    "error",
                    "message"
                  ],
                  "additionalProperties": false
                }
              }
            }
          },
          "500": {
            "description": "Internal error",
            "content": {
              "application/json": {
                "schema": {
                  "type": "object",
                  "properties": {
                    "error": {
                      "type": "string",
                      "const": "internal_error"
                    }
                  },
                  "required": [
                    "error"
                  ],
                  "additionalProperties": false
                }
              }
            }
          }
        },
        "security": [
          {
            "bearerAuth": []
          }
        ]
      }
    },
    "/internal/tools/tasks/delete": {
      "post": {
        "tags": [
          "Tasks"
        ],
        "summary": "Delete task",
        "requestBody": {
          "required": true,
          "content": {
            "application/json": {
              "schema": {
                "type": "object",
                "properties": {
                  "lane": {
                    "type": "string",
                    "enum": [
                      "interactive",
                      "scheduled"
                    ]
                  },
                  "id": {
                    "type": "string",
                    "minLength": 1
                  },
                  "reason": {
                    "type": "string",
                    "minLength": 1
                  }
                },
                "required": [
                  "lane",
                  "id"
                ],
                "additionalProperties": false
              }
            }
          }
        },
        "responses": {
          "200": {
            "description": "Task deleted",
            "content": {
              "application/json": {
                "schema": {
                  "type": "object",
                  "propertyNames": {
                    "type": "string"
                  },
                  "additionalProperties": {}
                }
              }
            }
          },
          "400": {
            "description": "Invalid request",
            "content": {
              "application/json": {
                "schema": {
                  "type": "object",
                  "properties": {
                    "error": {
                      "type": "string",
                      "const": "invalid_request"
                    },
                    "details": {
                      "type": "array",
                      "items": {}
                    }
                  },
                  "required": [
                    "error"
                  ],
                  "additionalProperties": false
                }
              }
            }
          },
          "401": {
            "description": "Unauthorized",
            "content": {
              "application/json": {
                "schema": {
                  "type": "object",
                  "properties": {
                    "error": {
                      "type": "string",
                      "const": "unauthorized"
                    }
                  },
                  "required": [
                    "error"
                  ],
                  "additionalProperties": false
                }
              }
            }
          },
          "403": {
            "description": "Lane forbidden",
            "content": {
              "application/json": {
                "schema": {
                  "type": "object",
                  "properties": {
                    "error": {
                      "type": "string",
                      "const": "lane_forbidden"
                    },
                    "message": {
                      "type": "string",
                      "minLength": 1
                    }
                  },
                  "required": [
                    "error",
                    "message"
                  ],
                  "additionalProperties": false
                }
              }
            }
          },
          "500": {
            "description": "Internal error",
            "content": {
              "application/json": {
                "schema": {
                  "type": "object",
                  "properties": {
                    "error": {
                      "type": "string",
                      "const": "internal_error"
                    }
                  },
                  "required": [
                    "error"
                  ],
                  "additionalProperties": false
                }
              }
            }
          }
        },
        "security": [
          {
            "bearerAuth": []
          }
        ]
      }
    },
    "/internal/tools/tasks/list": {
      "post": {
        "tags": [
          "Tasks"
        ],
        "summary": "List tasks",
        "requestBody": {
          "required": true,
          "content": {
            "application/json": {
              "schema": {
                "type": "object",
                "properties": {
                  "lane": {
                    "type": "string",
                    "enum": [
                      "interactive",
                      "scheduled"
                    ]
                  }
                },
                "required": [
                  "lane"
                ],
                "additionalProperties": false
              }
            }
          }
        },
        "responses": {
          "200": {
            "description": "Task list",
            "content": {
              "application/json": {
                "schema": {
                  "type": "object",
                  "propertyNames": {
                    "type": "string"
                  },
                  "additionalProperties": {}
                }
              }
            }
          },
          "400": {
            "description": "Invalid request",
            "content": {
              "application/json": {
                "schema": {
                  "type": "object",
                  "properties": {
                    "error": {
                      "type": "string",
                      "const": "invalid_request"
                    },
                    "details": {
                      "type": "array",
                      "items": {}
                    }
                  },
                  "required": [
                    "error"
                  ],
                  "additionalProperties": false
                }
              }
            }
          },
          "401": {
            "description": "Unauthorized",
            "content": {
              "application/json": {
                "schema": {
                  "type": "object",
                  "properties": {
                    "error": {
                      "type": "string",
                      "const": "unauthorized"
                    }
                  },
                  "required": [
                    "error"
                  ],
                  "additionalProperties": false
                }
              }
            }
          },
          "500": {
            "description": "Internal error",
            "content": {
              "application/json": {
                "schema": {
                  "type": "object",
                  "properties": {
                    "error": {
                      "type": "string",
                      "const": "internal_error"
                    }
                  },
                  "required": [
                    "error"
                  ],
                  "additionalProperties": false
                }
              }
            }
          }
        },
        "security": [
          {
            "bearerAuth": []
          }
        ]
      }
    },
    "/internal/tools/tasks/failures/check": {
      "post": {
        "tags": [
          "Tasks"
        ],
        "summary": "Check recent task failures",
        "requestBody": {
          "required": true,
          "content": {
            "application/json": {
              "schema": {
                "type": "object",
                "properties": {
                  "lane": {
                    "type": "string",
                    "enum": [
                      "interactive",
                      "scheduled"
                    ]
                  },
                  "sessionId": {
                    "type": "string",
                    "minLength": 1
                  },
                  "lookbackMinutes": {
                    "type": "integer",
                    "minimum": 5,
                    "maximum": 1440
                  },
                  "maxFailures": {
                    "type": "integer",
                    "minimum": 1,
                    "maximum": 200
                  },
                  "threshold": {
                    "type": "integer",
                    "minimum": 1,
                    "maximum": 50
                  },
                  "notify": {
                    "type": "boolean"
                  },
                  "chatId": {
                    "type": "integer",
                    "exclusiveMinimum": 0,
                    "maximum": 9007199254740991
                  }
                },
                "required": [
                  "lane"
                ],
                "additionalProperties": false
              }
            }
          }
        },
        "responses": {
          "200": {
            "description": "Failure check result",
            "content": {
              "application/json": {
                "schema": {
                  "type": "object",
                  "propertyNames": {
                    "type": "string"
                  },
                  "additionalProperties": {}
                }
              }
            }
          },
          "400": {
            "description": "Invalid request",
            "content": {
              "application/json": {
                "schema": {
                  "type": "object",
                  "properties": {
                    "error": {
                      "type": "string",
                      "const": "invalid_request"
                    },
                    "details": {
                      "type": "array",
                      "items": {}
                    }
                  },
                  "required": [
                    "error"
                  ],
                  "additionalProperties": false
                }
              }
            }
          },
          "401": {
            "description": "Unauthorized",
            "content": {
              "application/json": {
                "schema": {
                  "type": "object",
                  "properties": {
                    "error": {
                      "type": "string",
                      "const": "unauthorized"
                    }
                  },
                  "required": [
                    "error"
                  ],
                  "additionalProperties": false
                }
              }
            }
          },
          "500": {
            "description": "Internal error",
            "content": {
              "application/json": {
                "schema": {
                  "type": "object",
                  "properties": {
                    "error": {
                      "type": "string",
                      "const": "internal_error"
                    }
                  },
                  "required": [
                    "error"
                  ],
                  "additionalProperties": false
                }
              }
            }
          }
        },
        "security": [
          {
            "bearerAuth": []
          }
        ]
      }
    },
    "/internal/tools/notification-profile/get": {
      "post": {
        "tags": [
          "Tools"
        ],
        "summary": "Get notification profile",
        "requestBody": {
          "required": true,
          "content": {
            "application/json": {
              "schema": {
                "type": "object",
                "properties": {
                  "lane": {
                    "type": "string",
                    "enum": [
                      "interactive",
                      "scheduled"
                    ]
                  }
                },
                "required": [
                  "lane"
                ],
                "additionalProperties": false
              }
            }
          }
        },
        "responses": {
          "200": {
            "description": "Notification profile",
            "content": {
              "application/json": {
                "schema": {
                  "type": "object",
                  "propertyNames": {
                    "type": "string"
                  },
                  "additionalProperties": {}
                }
              }
            }
          },
          "400": {
            "description": "Invalid request",
            "content": {
              "application/json": {
                "schema": {
                  "type": "object",
                  "properties": {
                    "error": {
                      "type": "string",
                      "const": "invalid_request"
                    },
                    "details": {
                      "type": "array",
                      "items": {}
                    }
                  },
                  "required": [
                    "error"
                  ],
                  "additionalProperties": false
                }
              }
            }
          },
          "401": {
            "description": "Unauthorized",
            "content": {
              "application/json": {
                "schema": {
                  "type": "object",
                  "properties": {
                    "error": {
                      "type": "string",
                      "const": "unauthorized"
                    }
                  },
                  "required": [
                    "error"
                  ],
                  "additionalProperties": false
                }
              }
            }
          },
          "500": {
            "description": "Internal error",
            "content": {
              "application/json": {
                "schema": {
                  "type": "object",
                  "properties": {
                    "error": {
                      "type": "string",
                      "const": "internal_error"
                    }
                  },
                  "required": [
                    "error"
                  ],
                  "additionalProperties": false
                }
              }
            }
          }
        },
        "security": [
          {
            "bearerAuth": []
          }
        ]
      }
    },
    "/internal/tools/notification-profile/set": {
      "post": {
        "tags": [
          "Tools"
        ],
        "summary": "Set notification profile",
        "requestBody": {
          "required": true,
          "content": {
            "application/json": {
              "schema": {
                "type": "object",
                "properties": {
                  "lane": {
                    "type": "string",
                    "enum": [
                      "interactive",
                      "scheduled"
                    ]
                  },
                  "timezone": {
                    "type": "string",
                    "minLength": 1
                  },
                  "quietHoursStart": {
                    "anyOf": [
                      {
                        "type": "string",
                        "pattern": "^(?:[01]?\\d|2[0-3]):[0-5]\\d$"
                      },
                      {
                        "type": "null"
                      }
                    ]
                  },
                  "quietHoursEnd": {
                    "anyOf": [
                      {
                        "type": "string",
                        "pattern": "^(?:[01]?\\d|2[0-3]):[0-5]\\d$"
                      },
                      {
                        "type": "null"
                      }
                    ]
                  },
                  "heartbeatMorning": {
                    "anyOf": [
                      {
                        "type": "string",
                        "pattern": "^(?:[01]?\\d|2[0-3]):[0-5]\\d$"
                      },
                      {
                        "type": "null"
                      }
                    ]
                  },
                  "heartbeatMidday": {
                    "anyOf": [
                      {
                        "type": "string",
                        "pattern": "^(?:[01]?\\d|2[0-3]):[0-5]\\d$"
                      },
                      {
                        "type": "null"
                      }
                    ]
                  },
                  "heartbeatEvening": {
                    "anyOf": [
                      {
                        "type": "string",
                        "pattern": "^(?:[01]?\\d|2[0-3]):[0-5]\\d$"
                      },
                      {
                        "type": "null"
                      }
                    ]
                  },
                  "heartbeatCadenceMinutes": {
                    "anyOf": [
                      {
                        "type": "integer",
                        "minimum": 30,
                        "maximum": 1440
                      },
                      {
                        "type": "null"
                      }
                    ]
                  },
                  "heartbeatOnlyIfSignal": {
                    "type": "boolean"
                  },
                  "interactiveContextWindowSize": {
                    "type": "integer",
                    "minimum": 5,
                    "maximum": 200
                  },
                  "contextRetentionCap": {
                    "type": "integer",
                    "minimum": 5,
                    "maximum": 200
                  },
                  "quietMode": {
                    "type": "string",
                    "enum": [
                      "critical_only",
                      "off"
                    ]
                  },
                  "muteUntil": {
                    "anyOf": [
                      {
                        "type": "integer",
                        "minimum": -9007199254740991,
                        "maximum": 9007199254740991
                      },
                      {
                        "type": "null"
                      }
                    ]
                  },
                  "muteForMinutes": {
                    "type": "integer",
                    "minimum": 1,
                    "maximum": 10080
                  },
                  "markOnboardingComplete": {
                    "type": "boolean"
                  }
                },
                "required": [
                  "lane"
                ],
                "additionalProperties": false
              }
            }
          }
        },
        "responses": {
          "200": {
            "description": "Updated notification profile",
            "content": {
              "application/json": {
                "schema": {
                  "type": "object",
                  "propertyNames": {
                    "type": "string"
                  },
                  "additionalProperties": {}
                }
              }
            }
          },
          "400": {
            "description": "Invalid request",
            "content": {
              "application/json": {
                "schema": {
                  "type": "object",
                  "properties": {
                    "error": {
                      "type": "string",
                      "const": "invalid_request"
                    },
                    "details": {
                      "type": "array",
                      "items": {}
                    }
                  },
                  "required": [
                    "error"
                  ],
                  "additionalProperties": false
                }
              }
            }
          },
          "401": {
            "description": "Unauthorized",
            "content": {
              "application/json": {
                "schema": {
                  "type": "object",
                  "properties": {
                    "error": {
                      "type": "string",
                      "const": "unauthorized"
                    }
                  },
                  "required": [
                    "error"
                  ],
                  "additionalProperties": false
                }
              }
            }
          },
          "500": {
            "description": "Internal error",
            "content": {
              "application/json": {
                "schema": {
                  "type": "object",
                  "properties": {
                    "error": {
                      "type": "string",
                      "const": "internal_error"
                    }
                  },
                  "required": [
                    "error"
                  ],
                  "additionalProperties": false
                }
              }
            }
          }
        },
        "security": [
          {
            "bearerAuth": []
          }
        ]
      }
    },
    "/internal/tools/prompts/watchdog/get": {
      "post": {
        "tags": [
          "Tools"
        ],
        "summary": "Get watchdog prompt",
        "requestBody": {
          "required": true,
          "content": {
            "application/json": {
              "schema": {
                "type": "object",
                "properties": {
                  "lane": {
                    "default": "interactive",
                    "type": "string",
                    "enum": [
                      "interactive",
                      "scheduled"
                    ]
                  }
                },
                "required": [
                  "lane"
                ],
                "additionalProperties": false
              }
            }
          }
        },
        "responses": {
          "200": {
            "description": "Watchdog prompt",
            "content": {
              "application/json": {
                "schema": {
                  "type": "object",
                  "propertyNames": {
                    "type": "string"
                  },
                  "additionalProperties": {}
                }
              }
            }
          },
          "400": {
            "description": "Invalid request",
            "content": {
              "application/json": {
                "schema": {
                  "type": "object",
                  "properties": {
                    "error": {
                      "type": "string",
                      "const": "invalid_request"
                    },
                    "details": {
                      "type": "array",
                      "items": {}
                    }
                  },
                  "required": [
                    "error"
                  ],
                  "additionalProperties": false
                }
              }
            }
          },
          "401": {
            "description": "Unauthorized",
            "content": {
              "application/json": {
                "schema": {
                  "type": "object",
                  "properties": {
                    "error": {
                      "type": "string",
                      "const": "unauthorized"
                    }
                  },
                  "required": [
                    "error"
                  ],
                  "additionalProperties": false
                }
              }
            }
          },
          "500": {
            "description": "Internal error",
            "content": {
              "application/json": {
                "schema": {
                  "type": "object",
                  "properties": {
                    "error": {
                      "type": "string",
                      "const": "internal_error"
                    }
                  },
                  "required": [
                    "error"
                  ],
                  "additionalProperties": false
                }
              }
            }
          },
          "503": {
            "description": "Service unavailable",
            "content": {
              "application/json": {
                "schema": {
                  "type": "object",
                  "properties": {
                    "error": {
                      "type": "string",
                      "const": "service_unavailable"
                    }
                  },
                  "required": [
                    "error"
                  ],
                  "additionalProperties": false
                }
              }
            }
          }
        },
        "security": [
          {
            "bearerAuth": []
          }
        ]
      }
    },
    "/internal/tools/prompts/watchdog/set": {
      "post": {
        "tags": [
          "Tools"
        ],
        "summary": "Set watchdog prompt",
        "requestBody": {
          "required": true,
          "content": {
            "application/json": {
              "schema": {
                "type": "object",
                "properties": {
                  "lane": {
                    "default": "interactive",
                    "type": "string",
                    "enum": [
                      "interactive",
                      "scheduled"
                    ]
                  },
                  "content": {
                    "type": "string",
                    "minLength": 1
                  }
                },
                "required": [
                  "lane",
                  "content"
                ],
                "additionalProperties": false
              }
            }
          }
        },
        "responses": {
          "200": {
            "description": "Watchdog prompt updated",
            "content": {
              "application/json": {
                "schema": {
                  "type": "object",
                  "propertyNames": {
                    "type": "string"
                  },
                  "additionalProperties": {}
                }
              }
            }
          },
          "400": {
            "description": "Invalid request",
            "content": {
              "application/json": {
                "schema": {
                  "type": "object",
                  "properties": {
                    "error": {
                      "type": "string",
                      "const": "invalid_request"
                    },
                    "details": {
                      "type": "array",
                      "items": {}
                    }
                  },
                  "required": [
                    "error"
                  ],
                  "additionalProperties": false
                }
              }
            }
          },
          "401": {
            "description": "Unauthorized",
            "content": {
              "application/json": {
                "schema": {
                  "type": "object",
                  "properties": {
                    "error": {
                      "type": "string",
                      "const": "unauthorized"
                    }
                  },
                  "required": [
                    "error"
                  ],
                  "additionalProperties": false
                }
              }
            }
          },
          "500": {
            "description": "Internal error",
            "content": {
              "application/json": {
                "schema": {
                  "type": "object",
                  "properties": {
                    "error": {
                      "type": "string",
                      "const": "internal_error"
                    }
                  },
                  "required": [
                    "error"
                  ],
                  "additionalProperties": false
                }
              }
            }
          },
          "503": {
            "description": "Service unavailable",
            "content": {
              "application/json": {
                "schema": {
                  "type": "object",
                  "properties": {
                    "error": {
                      "type": "string",
                      "const": "service_unavailable"
                    }
                  },
                  "required": [
                    "error"
                  ],
                  "additionalProperties": false
                }
              }
            }
          }
        },
        "security": [
          {
            "bearerAuth": []
          }
        ]
      }
    },
    "/internal/tools/tasks/audit/list": {
      "post": {
        "tags": [
          "Tasks"
        ],
        "summary": "List recent task and command audit entries",
        "requestBody": {
          "required": true,
          "content": {
            "application/json": {
              "schema": {
                "type": "object",
                "properties": {
                  "lane": {
                    "type": "string",
                    "enum": [
                      "interactive",
                      "scheduled"
                    ]
                  },
                  "limit": {
                    "type": "integer",
                    "minimum": 1,
                    "maximum": 200
                  }
                },
                "required": [
                  "lane"
                ],
                "additionalProperties": false
              }
            }
          }
        },
        "responses": {
          "200": {
            "description": "Recent audit entries",
            "content": {
              "application/json": {
                "schema": {
                  "type": "object",
                  "properties": {
                    "taskAudit": {
                      "type": "array",
                      "items": {}
                    },
                    "commandAudit": {
                      "type": "array",
                      "items": {}
                    }
                  },
                  "required": [
                    "taskAudit",
                    "commandAudit"
                  ],
                  "additionalProperties": false
                }
              }
            }
          },
          "400": {
            "description": "Invalid request",
            "content": {
              "application/json": {
                "schema": {
                  "type": "object",
                  "properties": {
                    "error": {
                      "type": "string",
                      "const": "invalid_request"
                    },
                    "details": {
                      "type": "array",
                      "items": {}
                    }
                  },
                  "required": [
                    "error"
                  ],
                  "additionalProperties": false
                }
              }
            }
          },
          "401": {
            "description": "Unauthorized",
            "content": {
              "application/json": {
                "schema": {
                  "type": "object",
                  "properties": {
                    "error": {
                      "type": "string",
                      "const": "unauthorized"
                    }
                  },
                  "required": [
                    "error"
                  ],
                  "additionalProperties": false
                }
              }
            }
          },
          "500": {
            "description": "Internal error",
            "content": {
              "application/json": {
                "schema": {
                  "type": "object",
                  "properties": {
                    "error": {
                      "type": "string",
                      "const": "internal_error"
                    }
                  },
                  "required": [
                    "error"
                  ],
                  "additionalProperties": false
                }
              }
            }
          }
        },
        "security": [
          {
            "bearerAuth": []
          }
        ]
      }
    }
  }
}